basechange/__init__.py
basechange/__main__.py
basechange/factories.py
basechange/geometry.py
basechange/io.py
basemesh/__init__.py
basemesh/_containers.py
basemesh/_interpolation.py
basemesh/_mesh.py
basemesh/_meshing.py
basemesh/_stringdefs.py
basemesh/abc.py
basemesh/basechange.py
basemesh/errors.py
basemesh/log.py
basemesh/py.typed
basemesh/types.py
basemesh/utils.py
basemesh/_algorithms/__init__.py
basemesh/_algorithms/_algorithms_c.cp311-win_amd64.pyd
basemesh/_algorithms/_algorithms_py.py
basemesh/_pslg_builder/__init__.py
basemesh/_pslg_builder/_builder.py
basemesh/_pslg_builder/_geometry.py
basemesh/triangle/__init__.py
basemesh/triangle/_geometry.py
basemesh/triangle/_markers.py
basemesh/triangle/_serialisers.py
basemesh/triangle/_triangulate.py
basemesh/triangle/errors.py
basemesh/triangle/io.py
basemesh/triangle/bin/triangle_32.exe
basemesh/triangle/bin/triangle_linux_32
basemesh/triangle/bin/triangle_linux_64
meshtool/__init__.py
meshtool/core.py
meshtool/factories.py
BASEmesh-2.2.0.post1.dist-info/LICENSE
BASEmesh-2.2.0.post1.dist-info/METADATA
BASEmesh-2.2.0.post1.dist-info/WHEEL
BASEmesh-2.2.0.post1.dist-info/top_level.txt
BASEmesh-2.2.0.post1.dist-info/RECORD
