Metadata-Version: 2.1
Name: BASEmesh
Version: 2.2.0.post1
Summary: Pre-processing and mesh generation toolkit for BASEMENT.
Home-page: https://gitlab.ethz.ch/vaw/public/basemesh-v2/
Author: ETH Zürich
Maintainer-email: seidelmann@vaw.ethz.ch
License: GNU General Public License v3 (GPLv3)
Classifier: Development Status :: 4 - Beta
Classifier: License :: OSI Approved :: GNU General Public License v3 (GPLv3)
Classifier: Programming Language :: Python :: 3.7
Classifier: Typing :: Typed
License-File: LICENSE
Requires-Dist: numpy
Requires-Dist: py2dm (>=0.2.2)
